<?xml version="1.0" encoding="utf-8" standalone="no"?>
<!--Sample XML file generated by XMLSpy v2006 sp2 U (http://www.altova.com)-->
<mapStyle includeBackgrounddatabases="false" scale="10000" fileVersion="2" xmlns:xsi="http://www.w3.org/2001/XMLSchema-instance">
	<roadAlgorithm splitKetens="false"/>
	<nameAlgorithm unplacableEnabled="true" textOnPath="true" unplacableBlockOrder="grid Nr Name" unplacableAbbreviate="false" unplacableWithLines="true" unplacableNumbersUnique="false" lineSpacing="120">
		<unplacableBlockText xsi:type="textDraw" enabled="false" alignment="downleft" capitalMode="noCaps" font="helvetica" relHeight="100" spacing="0" slant="0" underline="false">
			<fontDraw>
				<line enabled="false">
					<color r="255" g="255" b="255" overprint="false"/>
					<size size="1" units="1/10th millimeter" isRelative="false"/>
					<style size="0" units="1/10th millimeter" isRelative="false" style="solid"/>
				</line>
				<fillColor enabled="true" r="54" g="54" b="54" overprint="false"/>
			</fontDraw>
			<size size="1290" units="micrometer" isRelative="false"/>
			<boxDraw enabled="false" extraHeight="0">
				<shape shapekind="rectangle">
					<line enabled="false">
						<color r="255" g="255" b="255" overprint="false"/>
						<size size="1" units="1/10th millimeter" isRelative="false"/>
						<style size="0" units="1/10th millimeter" isRelative="false" style="solid"/>
					</line>
					<fillColor enabled="true" r="54" g="54" b="54" overprint="false"/>
				</shape>
			</boxDraw>
		</unplacableBlockText>
		<overrideUnplacableColor xsi:type="drawSpec">
			<line enabled="false">
				<color r="255" g="255" b="255" overprint="true"/>
				<size size="0" units="kilometer" isRelative="false"/>
				<style size="0" units="kilometer" isRelative="false" style="solid"/>
			</line>
			<fillColor enabled="false" r="255" g="255" b="255" overprint="true"/>
		</overrideUnplacableColor>
	</nameAlgorithm>
	<layer xsi:type="epsLayer" enabled="true" name="administrative Base Data names neighbourhood" KindMain="EPS-layers" KindSub="" id="epslayer.generic.1" xmlns:xsi="http://www.w3.org/2001/XMLSchema-instance"/>
	<userstyle xsi:type="polygonaluserstyle" enabled="true" name="Neighbourhood Name small" overwriteRoadclass="other" namePattern="(.*)" KindMain="Boundaries" KindSub="Neighbourhood" deduplicateNames="false" xmlns:xsi="http://www.w3.org/2001/XMLSchema-instance">
		<criteria>
			<equation oper="eq" fieldname="Categ" value="Neighbourhood"/>
		</criteria>
		<textDraw xsi:type="flexTextDraw" enabled="true" alignment="left" capitalMode="as_is" font="helvetica-Bold" relHeight="100" spacing="0" slant="0" underline="false" flexEnabled="false">
			<fontDraw>
				<line enabled="false">
					<color r="255" g="255" b="255" overprint="false"/>
					<size size="1" units="1/10th millimeter" isRelative="false"/>
					<style size="0" units="1/10th millimeter" isRelative="false" style="solid"/>
				</line>
				<fillColor enabled="true" r="140" g="140" b="140" overprint="true"/>
			</fontDraw>
			<size size="1" units="points" isRelative="false"/>
			<boxDraw enabled="false" extraHeight="0">
				<shape shapekind="rectangle">
					<line enabled="false">
						<color r="255" g="255" b="255" overprint="false"/>
						<size size="1" units="1/10th millimeter" isRelative="false"/>
						<style size="0" units="1/10th millimeter" isRelative="false" style="solid"/>
					</line>
					<fillColor enabled="true" r="95" g="95" b="95" overprint="false"/>
				</shape>
			</boxDraw>
			<flexSize min="100" max="200"/>
			<flexSpacing min="100" max="667"/>
		</textDraw>
		<namePosition name="fullyInside"/>
		<namePosition name="partlyInside"/>
	</userstyle>
	<layer xsi:type="epsLayer" enabled="true" name="administrative Base Data names residential" KindMain="EPS-layers" KindSub="" id="epslayer.generic.2" xmlns:xsi="http://www.w3.org/2001/XMLSchema-instance"/>
	<userstyle xsi:type="polygonaluserstyle" enabled="true" name="Residential name small" overwriteRoadclass="other" namePattern="(.*)" KindMain="Boundaries" KindSub="Residential" deduplicateNames="false" xmlns:xsi="http://www.w3.org/2001/XMLSchema-instance">
		<criteria>
			<equation oper="eq" fieldname="Categ" value="Residential"/>
		</criteria>
		<textDraw xsi:type="flexTextDraw" enabled="true" alignment="left" capitalMode="as_is" font="helvetica" relHeight="100" spacing="0" slant="0" underline="false" flexEnabled="false">
			<fontDraw>
				<line enabled="false">
					<color r="255" g="255" b="255" overprint="false"/>
					<size size="1" units="1/10th millimeter" isRelative="false"/>
					<style size="0" units="1/10th millimeter" isRelative="false" style="solid"/>
				</line>
				<fillColor enabled="true" r="115" g="115" b="115" overprint="true"/>
			</fontDraw>
			<size size="1" units="points" isRelative="false"/>
			<boxDraw enabled="false" extraHeight="0">
				<shape shapekind="rectangle">
					<line enabled="false">
						<color r="255" g="255" b="255" overprint="false"/>
						<size size="1" units="1/10th millimeter" isRelative="false"/>
						<style size="0" units="1/10th millimeter" isRelative="false" style="solid"/>
					</line>
					<fillColor enabled="true" r="95" g="95" b="95" overprint="false"/>
				</shape>
			</boxDraw>
			<flexSize min="100" max="200"/>
			<flexSpacing min="100" max="667"/>
		</textDraw>
		<namePosition name="fullyInside"/>
		<namePosition name="partlyInside"/>
	</userstyle>
	<layer xsi:type="epsLayer" enabled="true" name="administrative Base Data names cities" KindMain="EPS-layers" KindSub="" id="epslayer.generic.3" xmlns:xsi="http://www.w3.org/2001/XMLSchema-instance"/>
	<layer xsi:type="polygonVectorLayer" enabled="false" name="City Boundary Name small" id="boundaries.cities.chloro" KindMain="Boundaries" KindSub="Cities" source="Here\Admin\City.lim" deduplicateNames="false" xmlns:xsi="http://www.w3.org/2001/XMLSchema-instance">
		<polyDraw>
			<line enabled="false">
				<color r="179" g="179" b="179" overprint="false"/>
				<size size="2" units="1/10th millimeter" isRelative="false"/>
				<style size="0" units="kilometer" isRelative="false" style="solid"/>
			</line>
			<fillColor enabled="false" r="255" g="255" b="255" overprint="true"/>
		</polyDraw>
		<textDraw enabled="true" alignment="left" capitalMode="allCaps" font="helvetica-Bold" relHeight="100" spacing="0" slant="0" underline="false">
			<fontDraw>
				<line enabled="false">
					<color r="255" g="255" b="255" overprint="true"/>
					<size size="0" units="kilometer" isRelative="false"/>
					<style size="0" units="kilometer" isRelative="false" style="solid"/>
				</line>
				<fillColor enabled="true" r="0" g="0" b="0" overprint="false"/>
			</fontDraw>
			<size size="1" units="points" isRelative="false"/>
			<boxDraw enabled="false" extraHeight="10">
				<shape shapekind="rectangle">
					<line enabled="true">
						<color r="255" g="255" b="255" overprint="true"/>
						<size size="0" units="kilometer" isRelative="false"/>
						<style size="0" units="kilometer" isRelative="false" style="solid"/>
					</line>
					<fillColor enabled="true" r="255" g="255" b="255" overprint="true"/>
				</shape>
			</boxDraw>
		</textDraw>
		<namePosition name="fullyInside"/>
		<namePosition name="partlyInside"/>
	</layer>
	<layer xsi:type="epsLayer" enabled="true" name="administrative base data names regions" KindMain="EPS-layers" KindSub="" id="epslayer.generic.4" xmlns:xsi="http://www.w3.org/2001/XMLSchema-instance"/>
	<layer xsi:type="polygonVectorLayer" enabled="true" name="Region Boundary Name small" id="boundaries.regions.chloro" KindMain="Boundaries" KindSub="Regions" source="Here\Admin\Region.lim" deduplicateNames="false" xmlns:xsi="http://www.w3.org/2001/XMLSchema-instance">
		<polyDraw>
			<line enabled="false">
				<color r="153" g="153" b="153" overprint="true"/>
				<size size="3" units="1/10th millimeter" isRelative="false"/>
				<style size="0" units="kilometer" isRelative="false" style="solid"/>
			</line>
			<fillColor enabled="false" r="255" g="255" b="255" overprint="true"/>
		</polyDraw>
		<textDraw enabled="true" alignment="left" capitalMode="allCaps" font="helvetica-Bold" relHeight="100" spacing="0" slant="0" underline="false">
			<fontDraw>
				<line enabled="false">
					<color r="255" g="255" b="255" overprint="true"/>
					<size size="0" units="kilometer" isRelative="false"/>
					<style size="0" units="kilometer" isRelative="false" style="solid"/>
				</line>
				<fillColor enabled="true" r="0" g="0" b="0" overprint="false"/>
			</fontDraw>
			<size size="1" units="points" isRelative="false"/>
			<boxDraw enabled="false" extraHeight="10">
				<shape shapekind="rectangle">
					<line enabled="true">
						<color r="255" g="255" b="255" overprint="true"/>
						<size size="0" units="kilometer" isRelative="false"/>
						<style size="0" units="kilometer" isRelative="false" style="solid"/>
					</line>
					<fillColor enabled="true" r="255" g="255" b="255" overprint="true"/>
				</shape>
			</boxDraw>
		</textDraw>
		<namePosition name="fullyInside"/>
		<namePosition name="partlyInside"/>
	</layer>
	<layer xsi:type="epsLayer" enabled="true" name="administrative Base Data names  provinces/states" KindMain="EPS-layers" KindSub="" id="epslayer.generic.5" xmlns:xsi="http://www.w3.org/2001/XMLSchema-instance"/>
	<layer xsi:type="polygonVectorLayer" enabled="true" name="Procvince Boundary Name small" id="boundaries.provinces.chloro" KindMain="Boundaries" KindSub="Provinces" source="Here\Admin\Province.lim" deduplicateNames="false" xmlns:xsi="http://www.w3.org/2001/XMLSchema-instance">
		<polyDraw>
			<line enabled="false">
				<color r="127" g="127" b="127" overprint="true"/>
				<size size="4" units="1/10th millimeter" isRelative="false"/>
				<style size="0" units="kilometer" isRelative="false" style="solid"/>
			</line>
			<fillColor enabled="false" r="255" g="255" b="255" overprint="true"/>
		</polyDraw>
		<textDraw enabled="true" alignment="left" capitalMode="allCaps" font="helvetica-Bold" relHeight="100" spacing="0" slant="0" underline="false">
			<fontDraw>
				<line enabled="false">
					<color r="255" g="255" b="255" overprint="true"/>
					<size size="0" units="kilometer" isRelative="false"/>
					<style size="0" units="kilometer" isRelative="false" style="solid"/>
				</line>
				<fillColor enabled="true" r="0" g="0" b="0" overprint="true"/>
			</fontDraw>
			<size size="1" units="points" isRelative="false"/>
			<boxDraw enabled="false" extraHeight="10">
				<shape shapekind="rectangle">
					<line enabled="true">
						<color r="255" g="255" b="255" overprint="true"/>
						<size size="0" units="kilometer" isRelative="false"/>
						<style size="0" units="kilometer" isRelative="false" style="solid"/>
					</line>
					<fillColor enabled="true" r="255" g="255" b="255" overprint="true"/>
				</shape>
			</boxDraw>
		</textDraw>
		<namePosition name="fullyInside"/>
		<namePosition name="partlyInside"/>
	</layer>
	<layer xsi:type="epsLayer" enabled="true" name="administrative Base Data names countries" KindMain="EPS-layers" KindSub="" id="epslayer.generic.6" xmlns:xsi="http://www.w3.org/2001/XMLSchema-instance"/>
	<layer xsi:type="polygonVectorLayer" enabled="true" name="Country Boundary Name small" id="boundaries.countries.chloro" KindMain="Boundaries" KindSub="Countries" source="Here\Admin\Country.lim" deduplicateNames="false" xmlns:xsi="http://www.w3.org/2001/XMLSchema-instance">
		<polyDraw>
			<line enabled="false">
				<color r="102" g="102" b="102" overprint="true"/>
				<size size="5" units="1/10th millimeter" isRelative="false"/>
				<style size="0" units="kilometer" isRelative="false" style="solid"/>
			</line>
			<fillColor enabled="false" r="255" g="255" b="255" overprint="true"/>
		</polyDraw>
		<textDraw enabled="true" alignment="left" capitalMode="allCaps" font="helvetica-Bold" relHeight="100" spacing="0" slant="0" underline="false">
			<fontDraw>
				<line enabled="false">
					<color r="255" g="255" b="255" overprint="true"/>
					<size size="0" units="kilometer" isRelative="false"/>
					<style size="0" units="kilometer" isRelative="false" style="solid"/>
				</line>
				<fillColor enabled="true" r="0" g="0" b="0" overprint="false"/>
			</fontDraw>
			<size size="1" units="points" isRelative="false"/>
			<boxDraw enabled="false" extraHeight="10">
				<shape shapekind="rectangle">
					<line enabled="true">
						<color r="255" g="255" b="255" overprint="true"/>
						<size size="0" units="kilometer" isRelative="false"/>
						<style size="0" units="kilometer" isRelative="false" style="solid"/>
					</line>
					<fillColor enabled="true" r="255" g="255" b="255" overprint="true"/>
				</shape>
			</boxDraw>
		</textDraw>
		<namePosition name="fullyInside"/>
		<namePosition name="partlyInside"/>
	</layer>
	<layer xsi:type="epsLayer" enabled="true" name="administrative shapes cities fill" KindMain="EPS-layers" KindSub="" id="epslayer.generic.7" xmlns:xsi="http://www.w3.org/2001/XMLSchema-instance"/>
	<layer xsi:type="includeFileLayer" enabled="true" name="After Land 0" layerId="AfterLand0" KindMain="Special Constructions" KindSub="Layer in Node Draw Order" id="includelayer.afterland0"/>
	<layer xsi:type="epsLayer" enabled="true" name="island" KindMain="EPS-layers" KindSub="" id="epslayer.generic.8" xmlns:xsi="http://www.w3.org/2001/XMLSchema-instance"/>
	<polygongroup name="Landphase 1" perDb="true" KindMain="Landuse" KindSub="Landphase Landuse" id="landusegroup.landphase1">
		<polygonstyle enabled="true" name="Island" KindMain="Landuse" KindSub="Islands" id="landuse.islands.fill">
			<criteria>
				<equation oper="eq" fieldname="Categ" value="Island"/>
			</criteria>
			<polyDraw>
				<line enabled="false">
					<color r="95" g="95" b="95" overprint="false"/>
					<size size="1" units="1/10th millimeter" isRelative="false"/>
					<style size="0" units="1/10th millimeter" isRelative="false" style="solid"/>
				</line>
				<fillColor enabled="true" r="255" g="255" b="255" overprint="false"/>
			</polyDraw>
		</polygonstyle>
	</polygongroup>
	<layer xsi:type="epsLayer" enabled="true" name="administrative shapes countries fill" KindMain="EPS-layers" KindSub="" id="epslayer.generic.9" xmlns:xsi="http://www.w3.org/2001/XMLSchema-instance"/>
	<layer xsi:type="polygonVectorLayer" enabled="true" name="Country Boundary Polygon fill" id="boundaries.countries.chloro" KindMain="Boundaries" KindSub="Countries" source="Here\Admin\Country.lim" deduplicateNames="false" xmlns:xsi="http://www.w3.org/2001/XMLSchema-instance">
		<polyDraw>
			<line enabled="true">
				<color r="102" g="102" b="102" overprint="true"/>
				<size size="6" units="1/10th millimeter" isRelative="false"/>
				<style size="0" units="kilometer" isRelative="false" style="solid"/>
			</line>
			<fillColor enabled="true" r="255" g="255" b="255" overprint="true"/>
		</polyDraw>
		<textDraw enabled="false" alignment="left" capitalMode="allCaps" font="helvetica-Bold" relHeight="100" spacing="0" slant="0" underline="false">
			<fontDraw>
				<line enabled="false">
					<color r="255" g="255" b="255" overprint="true"/>
					<size size="0" units="kilometer" isRelative="false"/>
					<style size="0" units="kilometer" isRelative="false" style="solid"/>
				</line>
				<fillColor enabled="true" r="0" g="0" b="0" overprint="false"/>
			</fontDraw>
			<size size="1" units="points" isRelative="false"/>
			<boxDraw enabled="true" extraHeight="0">
				<shape shapekind="rectangle">
					<line enabled="true">
						<color r="255" g="255" b="255" overprint="true"/>
						<size size="0" units="kilometer" isRelative="false"/>
						<style size="0" units="kilometer" isRelative="false" style="solid"/>
					</line>
					<fillColor enabled="true" r="255" g="255" b="255" overprint="true"/>
				</shape>
			</boxDraw>
		</textDraw>
		<namePosition name="fullyInside"/>
		<namePosition name="partlyInside"/>
	</layer>
	<layer xsi:type="epsLayer" enabled="true" name="administrative shapes provinces/states fill" KindMain="EPS-layers" KindSub="" id="epslayer.generic.10" xmlns:xsi="http://www.w3.org/2001/XMLSchema-instance"/>
	<layer xsi:type="polygonVectorLayer" enabled="true" name="province Boundary Polygon fill" id="boundaries.provinces.chloro" KindMain="Boundaries" KindSub="Provinces" source="Here\Admin\Province.lim" deduplicateNames="false" xmlns:xsi="http://www.w3.org/2001/XMLSchema-instance">
		<polyDraw>
			<line enabled="true">
				<color r="127" g="127" b="127" overprint="true"/>
				<size size="4" units="1/10th millimeter" isRelative="false"/>
				<style size="0" units="kilometer" isRelative="false" style="solid"/>
			</line>
			<fillColor enabled="true" r="255" g="255" b="255" overprint="true"/>
		</polyDraw>
		<textDraw enabled="false" alignment="left" capitalMode="allCaps" font="helvetica-Bold" relHeight="100" spacing="0" slant="0" underline="false">
			<fontDraw>
				<line enabled="false">
					<color r="255" g="255" b="255" overprint="true"/>
					<size size="0" units="kilometer" isRelative="false"/>
					<style size="0" units="kilometer" isRelative="false" style="solid"/>
				</line>
				<fillColor enabled="true" r="0" g="0" b="0" overprint="false"/>
			</fontDraw>
			<size size="1" units="points" isRelative="false"/>
			<boxDraw enabled="true" extraHeight="0">
				<shape shapekind="rectangle">
					<line enabled="true">
						<color r="255" g="255" b="255" overprint="true"/>
						<size size="0" units="kilometer" isRelative="false"/>
						<style size="0" units="kilometer" isRelative="false" style="solid"/>
					</line>
					<fillColor enabled="true" r="255" g="255" b="255" overprint="true"/>
				</shape>
			</boxDraw>
		</textDraw>
		<namePosition name="fullyInside"/>
		<namePosition name="partlyInside"/>
	</layer>
	<layer xsi:type="epsLayer" enabled="true" name="administrative shapes regions fill" KindMain="EPS-layers" KindSub="" id="epslayer.generic.11" xmlns:xsi="http://www.w3.org/2001/XMLSchema-instance"/>
	<layer xsi:type="polygonVectorLayer" enabled="true" name="Region Boundary Polygon fill" id="boundaries.regions.chloro" KindMain="Boundaries" KindSub="Regions" source="Here\Admin\Region.lim" deduplicateNames="false" xmlns:xsi="http://www.w3.org/2001/XMLSchema-instance">
		<polyDraw>
			<line enabled="true">
				<color r="153" g="153" b="153" overprint="true"/>
				<size size="3" units="1/10th millimeter" isRelative="false"/>
				<style size="0" units="kilometer" isRelative="false" style="solid"/>
			</line>
			<fillColor enabled="true" r="255" g="255" b="255" overprint="true"/>
		</polyDraw>
		<textDraw enabled="false" alignment="left" capitalMode="allCaps" font="helvetica-Bold" relHeight="100" spacing="0" slant="0" underline="false">
			<fontDraw>
				<line enabled="false">
					<color r="255" g="255" b="255" overprint="true"/>
					<size size="0" units="kilometer" isRelative="false"/>
					<style size="0" units="kilometer" isRelative="false" style="solid"/>
				</line>
				<fillColor enabled="true" r="0" g="0" b="0" overprint="false"/>
			</fontDraw>
			<size size="1" units="points" isRelative="false"/>
			<boxDraw enabled="true" extraHeight="0">
				<shape shapekind="rectangle">
					<line enabled="true">
						<color r="255" g="255" b="255" overprint="true"/>
						<size size="0" units="kilometer" isRelative="false"/>
						<style size="0" units="kilometer" isRelative="false" style="solid"/>
					</line>
					<fillColor enabled="true" r="255" g="255" b="255" overprint="true"/>
				</shape>
			</boxDraw>
		</textDraw>
		<namePosition name="fullyInside"/>
		<namePosition name="partlyInside"/>
	</layer>
	<layer xsi:type="epsLayer" enabled="true" name="administrative shapes citties fill" KindMain="EPS-layers" KindSub="" id="epslayer.generic.12" xmlns:xsi="http://www.w3.org/2001/XMLSchema-instance"/>
	<layer xsi:type="polygonVectorLayer" enabled="true" name="City  Boundary Polygon fill" id="boundaries.cities.chloro" KindMain="Boundaries" KindSub="Cities" source="Here\Admin\City.lim" deduplicateNames="false" xmlns:xsi="http://www.w3.org/2001/XMLSchema-instance">
		<polyDraw>
			<line enabled="true">
				<color r="179" g="179" b="179" overprint="false"/>
				<size size="3" units="1/10th millimeter" isRelative="false"/>
				<style size="0" units="kilometer" isRelative="false" style="solid"/>
			</line>
			<fillColor enabled="true" r="255" g="255" b="255" overprint="true"/>
		</polyDraw>
		<textDraw enabled="false" alignment="left" capitalMode="allCaps" font="helvetica-Bold" relHeight="100" spacing="0" slant="0" underline="false">
			<fontDraw>
				<line enabled="false">
					<color r="255" g="255" b="255" overprint="true"/>
					<size size="0" units="kilometer" isRelative="false"/>
					<style size="0" units="kilometer" isRelative="false" style="solid"/>
				</line>
				<fillColor enabled="true" r="0" g="0" b="0" overprint="false"/>
			</fontDraw>
			<size size="1" units="points" isRelative="false"/>
			<boxDraw enabled="true" extraHeight="0">
				<shape shapekind="rectangle">
					<line enabled="true">
						<color r="255" g="255" b="255" overprint="true"/>
						<size size="0" units="kilometer" isRelative="false"/>
						<style size="0" units="kilometer" isRelative="false" style="solid"/>
					</line>
					<fillColor enabled="true" r="255" g="255" b="255" overprint="true"/>
				</shape>
			</boxDraw>
		</textDraw>
		<namePosition name="fullyInside"/>
		<namePosition name="partlyInside"/>
	</layer>
	<layer xsi:type="epsLayer" enabled="true" name="administrative shapes residential" KindMain="EPS-layers" KindSub="" id="epslayer.generic.13" xmlns:xsi="http://www.w3.org/2001/XMLSchema-instance"/>
	<polygongroup name="Landphase 3" perDb="false" KindMain="Landuse" KindSub="Landphase Landuse" id="landusegroup.landphase3">
		<polygonstyle enabled="true" name="Residential" KindMain="Boundaries" KindSub="Residential">
			<criteria>
				<equation oper="eq" fieldname="Categ" value="Residential"/>
			</criteria>
			<polyDraw>
				<line enabled="true">
					<color r="204" g="204" b="204" overprint="false"/>
					<size size="3" units="1/10th millimeter" isRelative="false"/>
					<style size="0" units="1/10th millimeter" isRelative="false" style="solid"/>
				</line>
				<fillColor enabled="true" r="255" g="255" b="255" overprint="false"/>
			</polyDraw>
		</polygonstyle>
	</polygongroup>
	<layer xsi:type="epsLayer" enabled="true" name="administrative shapes neighbourhood" KindMain="EPS-layers" KindSub="" id="epslayer.generic.14" xmlns:xsi="http://www.w3.org/2001/XMLSchema-instance"/>
	<polygongroup name="Landphase 4" perDb="false" KindMain="Landuse" KindSub="Landphase Landuse" id="landusegroup.landphase4">
		<polygonstyle enabled="true" name="Neighbourhood" KindMain="Boundaries" KindSub="Neighbourhood">
			<criteria>
				<equation oper="eq" fieldname="Categ" value="Neighbourhood"/>
			</criteria>
			<polyDraw>
				<line enabled="true">
					<color r="204" g="204" b="204" overprint="false"/>
					<size size="5" units="1/10th millimeter" isRelative="false"/>
					<style size="0" units="1/10th millimeter" isRelative="false" style="solid"/>
				</line>
				<fillColor enabled="true" r="255" g="255" b="255" overprint="false"/>
			</polyDraw>
		</polygonstyle>
	</polygongroup>
	<layer xsi:type="epsLayer" enabled="true" name="sea" KindMain="EPS-layers" KindSub="" id="epslayer.generic.15" xmlns:xsi="http://www.w3.org/2001/XMLSchema-instance"/>
	<polygongroup name="Landphase11" perDb="true" KindMain="Landuse" KindSub="Landphase Landuse" id="landusegroup.landphase11">
		<polygonstyle enabled="true" name="Sea" KindMain="Water" KindSub="Lakes / Seas">
			<criteria>
				<inset fieldname="Categ">
					<item value="Lake"/>
					<item value="River outline"/>
					<item value="Channel outline"/>
					<item value="Harbour outline"/>
					<item value="Yacht-basin"/>
					<item value="Bay"/>
					<item value="Delta"/>
					<item value="Sea   ."/>
					<item value="Ocean"/>
				</inset>
			</criteria>
			<polyDraw>
				<line enabled="false">
					<color r="153" g="178" b="204" overprint="false"/>
					<size size="1" units="1/10th millimeter" isRelative="false"/>
					<style size="0" units="1/10th millimeter" isRelative="false" style="solid"/>
				</line>
				<fillColor enabled="true" r="179" g="217" b="217" overprint="false"/>
			</polyDraw>
		</polygonstyle>
		<polygonstyle enabled="true" name="Island" KindMain="Landuse" KindSub="Islands" id="landuse.islands">
			<criteria>
				<equation oper="eq" fieldname="Categ" value="Island"/>
			</criteria>
			<polyDraw>
				<line enabled="false">
					<color r="95" g="95" b="95" overprint="false"/>
					<size size="1" units="1/10th millimeter" isRelative="false"/>
					<style size="0" units="1/10th millimeter" isRelative="false" style="solid"/>
				</line>
				<fillColor enabled="false" r="230" g="230" b="222" overprint="false"/>
			</polyDraw>
		</polygonstyle>
	</polygongroup>
	<layer xsi:type="epsLayer" enabled="true" name="administrative lines quarter" KindMain="EPS-layers" KindSub="" id="epslayer.generic.16" xmlns:xsi="http://www.w3.org/2001/XMLSchema-instance"/>
	<chainstyle enabled="true" name="Quarter Boundary Line" KindMain="Boundaries" KindSub="quarter">
		<criteria>
			<equation oper="eq" fieldname="UserCatPresent" value="Quarter boundary"/>
			<and>
				<inset fieldname="UserCatPresent" negate="true">
					<item value="Harbour outline"/>
					<item value="Sea   ."/>
					<item value="Ocean"/>
					<item value="Island"/>
				</inset>
			</and>
		</criteria>
		<lineDraw enabled="true">
			<color r="204" g="204" b="204" overprint="false"/>
			<size size="7" units="1/10th millimeter" isRelative="false"/>
			<style size="0" units="kilometer" isRelative="false" style="solid"/>
			<extension size="0" units="kilometer" isRelative="false"/>
		</lineDraw>
	</chainstyle>
	<layer xsi:type="epsLayer" enabled="true" name="administrative lines cities" KindMain="EPS-layers" KindSub="" id="epslayer.generic.17" xmlns:xsi="http://www.w3.org/2001/XMLSchema-instance"/>
	<chainstyle enabled="true" name="City Boundary Line" KindMain="Boundaries" KindSub="Cities">
		<criteria>
			<equation oper="eq" fieldname="UserCatPresent" value="City boundary"/>
			<and>
				<inset fieldname="UserCatPresent" negate="true">
					<item value="Harbour outline"/>
					<item value="Sea   ."/>
					<item value="Ocean"/>
					<item value="Island"/>
				</inset>
			</and>
		</criteria>
		<lineDraw enabled="true">
			<color r="179" g="179" b="179" overprint="false"/>
			<size size="3" units="1/10th millimeter" isRelative="false"/>
			<style size="0" units="kilometer" isRelative="false" style="solid"/>
			<extension size="0" units="kilometer" isRelative="false"/>
		</lineDraw>
	</chainstyle>
	<layer xsi:type="epsLayer" enabled="true" name="administrative lines regions" KindMain="EPS-layers" KindSub="" id="epslayer.generic.18" xmlns:xsi="http://www.w3.org/2001/XMLSchema-instance"/>
	<chainstyle enabled="true" name="Region Boundary Line" KindMain="Boundaries" KindSub="Regions">
		<criteria>
			<equation oper="eq" fieldname="UserCatPresent" value="Region boundary"/>
			<and>
				<inset fieldname="UserCatPresent" negate="true">
					<item value="Harbour outline"/>
					<item value="Sea   ."/>
					<item value="Ocean"/>
					<item value="Island"/>
				</inset>
			</and>
		</criteria>
		<lineDraw enabled="true">
			<color r="153" g="153" b="153" overprint="false"/>
			<size size="3" units="1/10th millimeter" isRelative="false"/>
			<style size="0" units="kilometer" isRelative="false" style="solid"/>
			<extension size="0" units="kilometer" isRelative="false"/>
		</lineDraw>
	</chainstyle>
	<layer xsi:type="epsLayer" enabled="true" name="administrative lines provinces/states" KindMain="EPS-layers" KindSub="" id="epslayer.generic.19" xmlns:xsi="http://www.w3.org/2001/XMLSchema-instance"/>
	<chainstyle enabled="true" name="Province Boundary Line" KindMain="Boundaries" KindSub="Provinces">
		<criteria>
			<equation oper="eq" fieldname="UserCatPresent" value="Province boundary"/>
			<and>
				<inset fieldname="UserCatPresent" negate="true">
					<item value="Harbour outline"/>
					<item value="Sea   ."/>
					<item value="Ocean"/>
					<item value="Island"/>
				</inset>
			</and>
		</criteria>
		<lineDraw enabled="true">
			<color r="127" g="127" b="127" overprint="false"/>
			<size size="4" units="1/10th millimeter" isRelative="false"/>
			<style size="0" units="kilometer" isRelative="false" style="solid"/>
			<extension size="0" units="kilometer" isRelative="false"/>
		</lineDraw>
	</chainstyle>
	<layer xsi:type="epsLayer" enabled="true" name="administrative lines countries" KindMain="EPS-layers" KindSub="" id="epslayer.generic.20" xmlns:xsi="http://www.w3.org/2001/XMLSchema-instance"/>
	<chainstyle enabled="true" name="Country Boundary Line" KindMain="Boundaries" KindSub="Countries">
		<criteria>
			<equation oper="eq" fieldname="UserCatPresent" value="Country boundary"/>
			<and>
				<inset fieldname="UserCatPresent" negate="true">
					<item value="Harbour outline"/>
					<item value="Sea   ."/>
					<item value="Ocean"/>
					<item value="Island"/>
				</inset>
			</and>
		</criteria>
		<lineDraw enabled="true">
			<color r="102" g="102" b="102" overprint="false"/>
			<size size="5" units="1/10th millimeter" isRelative="false"/>
			<style size="0" units="kilometer" isRelative="false" style="solid"/>
			<extension size="0" units="kilometer" isRelative="false"/>
		</lineDraw>
	</chainstyle>
	<layer xsi:type="includeFileLayer" enabled="true" name="After Landuse" layerId="AfterLanduse" KindMain="Special Constructions" KindSub="Layer in Node Draw Order" id="includelayer.afterlanduse"/>
	<layer xsi:type="includeFileLayer" enabled="true" name="After Names" layerId="AfterNames" KindMain="Special Constructions" KindSub="Layer in Node Draw Order" id="includelayer.afternames"/>
	<layer xsi:type="epsLayer" enabled="true" name="administrative names residential" KindMain="EPS-layers" KindSub="" id="epslayer.generic.21"/>
	<userstyle xsi:type="polygonaluserstyle" enabled="true" name="Residential name" overwriteRoadclass="other" namePattern="(.*)" KindMain="Boundaries" KindSub="Residential">
		<criteria>
			<equation oper="eq" fieldname="Categ" value="Residential"/>
		</criteria>
		<textDraw xsi:type="flexTextDraw" enabled="true" alignment="left" capitalMode="as_is" font="helvetica" relHeight="100" spacing="0" slant="0" underline="false" flexEnabled="true">
			<fontDraw>
				<line enabled="false">
					<color r="255" g="255" b="255" overprint="false"/>
					<size size="1" units="1/10th millimeter" isRelative="false"/>
					<style size="0" units="1/10th millimeter" isRelative="false" style="solid"/>
				</line>
				<fillColor enabled="true" r="115" g="115" b="115" overprint="false"/>
			</fontDraw>
			<size size="8" units="points" isRelative="false"/>
			<boxDraw enabled="false" extraHeight="0">
				<shape shapekind="rectangle">
					<line enabled="false">
						<color r="255" g="255" b="255" overprint="false"/>
						<size size="1" units="1/10th millimeter" isRelative="false"/>
						<style size="0" units="1/10th millimeter" isRelative="false" style="solid"/>
					</line>
					<fillColor enabled="true" r="95" g="95" b="95" overprint="false"/>
				</shape>
			</boxDraw>
			<flexSize min="75" max="100"/>
			<flexSpacing min="100" max="667"/>
		</textDraw>
		<namePosition name="fullyInside"/>
		<namePosition name="partlyInside"/>
	</userstyle>
	<layer xsi:type="epsLayer" enabled="true" name="administrative names neighbourhood" KindMain="EPS-layers" KindSub="" id="epslayer.generic.22"/>
	<userstyle xsi:type="polygonaluserstyle" enabled="true" name="Neighbourhood Name" overwriteRoadclass="other" namePattern="(.*)" KindMain="Boundaries" KindSub="Neighbourhood">
		<criteria>
			<equation oper="eq" fieldname="Categ" value="Neighbourhood"/>
		</criteria>
		<textDraw xsi:type="flexTextDraw" enabled="true" alignment="left" capitalMode="as_is" font="helvetica-Bold" relHeight="100" spacing="0" slant="0" underline="false" flexEnabled="true">
			<fontDraw>
				<line enabled="false">
					<color r="255" g="255" b="255" overprint="false"/>
					<size size="1" units="1/10th millimeter" isRelative="false"/>
					<style size="0" units="1/10th millimeter" isRelative="false" style="solid"/>
				</line>
				<fillColor enabled="true" r="140" g="140" b="140" overprint="false"/>
			</fontDraw>
			<size size="8" units="points" isRelative="false"/>
			<boxDraw enabled="false" extraHeight="0">
				<shape shapekind="rectangle">
					<line enabled="false">
						<color r="255" g="255" b="255" overprint="false"/>
						<size size="1" units="1/10th millimeter" isRelative="false"/>
						<style size="0" units="1/10th millimeter" isRelative="false" style="solid"/>
					</line>
					<fillColor enabled="true" r="95" g="95" b="95" overprint="false"/>
				</shape>
			</boxDraw>
			<flexSize min="75" max="100"/>
			<flexSpacing min="100" max="100"/>
		</textDraw>
		<namePosition name="fullyInside"/>
		<namePosition name="partlyInside"/>
	</userstyle>
	<layer xsi:type="epsLayer" enabled="true" name="administrative names cities" KindMain="EPS-layers" KindSub="" id="epslayer.generic.23" xmlns:xsi="http://www.w3.org/2001/XMLSchema-instance"/>
	<layer xsi:type="polygonVectorLayer" enabled="true" name="City Boundary Name" id="boundaries.cities.chloro" KindMain="Boundaries" KindSub="Cities" source="Here\Admin\City.lim" deduplicateNames="false" xmlns:xsi="http://www.w3.org/2001/XMLSchema-instance">
		<polyDraw>
			<line enabled="false">
				<color r="153" g="153" b="153" overprint="true"/>
				<size size="3" units="1/10th millimeter" isRelative="false"/>
				<style size="0" units="kilometer" isRelative="false" style="solid"/>
			</line>
			<fillColor enabled="false" r="255" g="255" b="255" overprint="true"/>
		</polyDraw>
		<textDraw enabled="true" alignment="left" capitalMode="allCaps" font="helvetica-Bold" relHeight="100" spacing="0" slant="0" underline="false">
			<fontDraw>
				<line enabled="false">
					<color r="255" g="255" b="255" overprint="true"/>
					<size size="0" units="kilometer" isRelative="false"/>
					<style size="0" units="kilometer" isRelative="false" style="solid"/>
				</line>
				<fillColor enabled="true" r="102" g="102" b="102" overprint="false"/>
			</fontDraw>
			<size size="7" units="points" isRelative="false"/>
			<boxDraw enabled="false" extraHeight="10">
				<shape shapekind="rectangle">
					<line enabled="true">
						<color r="255" g="255" b="255" overprint="true"/>
						<size size="0" units="kilometer" isRelative="false"/>
						<style size="0" units="kilometer" isRelative="false" style="solid"/>
					</line>
					<fillColor enabled="true" r="255" g="255" b="255" overprint="true"/>
				</shape>
			</boxDraw>
		</textDraw>
		<namePosition name="fullyInside"/>
		<namePosition name="partlyInside"/>
	</layer>
	<layer xsi:type="epsLayer" enabled="true" name="administrative names regions" KindMain="EPS-layers" KindSub="" id="epslayer.generic.24" xmlns:xsi="http://www.w3.org/2001/XMLSchema-instance"/>
	<layer xsi:type="polygonVectorLayer" enabled="true" name="Region Boundary Name" id="boundaries.regions.chloro" KindMain="Boundaries" KindSub="Regions" source="Here\Admin\Region.lim" deduplicateNames="false" xmlns:xsi="http://www.w3.org/2001/XMLSchema-instance">
		<polyDraw>
			<line enabled="false">
				<color r="153" g="153" b="153" overprint="true"/>
				<size size="3" units="1/10th millimeter" isRelative="false"/>
				<style size="0" units="kilometer" isRelative="false" style="solid"/>
			</line>
			<fillColor enabled="false" r="255" g="255" b="255" overprint="true"/>
		</polyDraw>
		<textDraw enabled="true" alignment="left" capitalMode="allCaps" font="helvetica-Bold" relHeight="100" spacing="0" slant="0" underline="false">
			<fontDraw>
				<line enabled="false">
					<color r="255" g="255" b="255" overprint="true"/>
					<size size="0" units="kilometer" isRelative="false"/>
					<style size="0" units="kilometer" isRelative="false" style="solid"/>
				</line>
				<fillColor enabled="true" r="51" g="51" b="51" overprint="false"/>
			</fontDraw>
			<size size="8" units="points" isRelative="false"/>
			<boxDraw enabled="false" extraHeight="10">
				<shape shapekind="rectangle">
					<line enabled="true">
						<color r="255" g="255" b="255" overprint="true"/>
						<size size="0" units="kilometer" isRelative="false"/>
						<style size="0" units="kilometer" isRelative="false" style="solid"/>
					</line>
					<fillColor enabled="true" r="255" g="255" b="255" overprint="true"/>
				</shape>
			</boxDraw>
		</textDraw>
		<namePosition name="fullyInside"/>
		<namePosition name="partlyInside"/>
	</layer>
	<layer xsi:type="epsLayer" enabled="true" name="administrative names provinces/states" KindMain="EPS-layers" KindSub="" id="epslayer.generic.25" xmlns:xsi="http://www.w3.org/2001/XMLSchema-instance"/>
	<layer xsi:type="polygonVectorLayer" enabled="true" name="Procvince Boundary Name" id="boundaries.provinces.chloro" KindMain="Boundaries" KindSub="Provinces" source="Here\Admin\Province.lim" deduplicateNames="false" xmlns:xsi="http://www.w3.org/2001/XMLSchema-instance">
		<polyDraw>
			<line enabled="false">
				<color r="127" g="127" b="127" overprint="true"/>
				<size size="4" units="1/10th millimeter" isRelative="false"/>
				<style size="0" units="kilometer" isRelative="false" style="solid"/>
			</line>
			<fillColor enabled="false" r="255" g="255" b="255" overprint="true"/>
		</polyDraw>
		<textDraw enabled="true" alignment="left" capitalMode="allCaps" font="helvetica-Bold" relHeight="100" spacing="0" slant="0" underline="false">
			<fontDraw>
				<line enabled="false">
					<color r="255" g="255" b="255" overprint="true"/>
					<size size="0" units="kilometer" isRelative="false"/>
					<style size="0" units="kilometer" isRelative="false" style="solid"/>
				</line>
				<fillColor enabled="true" r="25" g="25" b="25" overprint="false"/>
			</fontDraw>
			<size size="8" units="points" isRelative="false"/>
			<boxDraw enabled="false" extraHeight="10">
				<shape shapekind="rectangle">
					<line enabled="true">
						<color r="255" g="255" b="255" overprint="true"/>
						<size size="0" units="kilometer" isRelative="false"/>
						<style size="0" units="kilometer" isRelative="false" style="solid"/>
					</line>
					<fillColor enabled="true" r="255" g="255" b="255" overprint="true"/>
				</shape>
			</boxDraw>
		</textDraw>
		<namePosition name="fullyInside"/>
		<namePosition name="partlyInside"/>
	</layer>
	<admiPolygonstyle enabled="true" name="Dim Other Munis" KindMain="Landuse" KindSub="Dim Other Munis" id="landuse.dimothermunis.fill">
		<criteria>
			<equation oper="eq" fieldname="Level" value="8192"/>
			<and>
				<equation oper="eq" fieldname="InBookMuni" value="false"/>
			</and>
		</criteria>
		<polyDraw>
			<line enabled="false">
				<color r="95" g="95" b="95" overprint="false"/>
				<size size="1" units="1/10th millimeter" isRelative="false"/>
				<style size="0" units="1/10th millimeter" isRelative="false" style="solid"/>
			</line>
			<fillColor enabled="true" r="255" g="255" b="255" overprint="false"/>
		</polyDraw>
	</admiPolygonstyle>
	<layer xsi:type="includeFileLayer" enabled="true" name="After Land 1" layerId="AfterLand1" KindMain="Special Constructions" KindSub="Layer in Node Draw Order" id="includelayer.afterland1"/>
	<layer xsi:type="includeFileLayer" enabled="true" name="After Land 2" layerId="AfterLand2" KindMain="Special Constructions" KindSub="Layer in Node Draw Order" id="includelayer.afterland2"/>
	<layer xsi:type="includeFileLayer" enabled="true" name="After Land 3" layerId="AfterLand3" KindMain="Special Constructions" KindSub="Layer in Node Draw Order" id="includelayer.afterland3"/>
	<layer xsi:type="includeFileLayer" enabled="true" name="After Land 4" layerId="AfterLand4" KindMain="Special Constructions" KindSub="Layer in Node Draw Order" id="includelayer.afterland4"/>
	<layer xsi:type="includeFileLayer" enabled="true" name="After Land 5" layerId="AfterLand5" KindMain="Special Constructions" KindSub="Layer in Node Draw Order" id="includelayer.afterland5"/>
	<layer xsi:type="includeFileLayer" enabled="true" name="After Land 6" layerId="AfterLand6" KindMain="Special Constructions" KindSub="Layer in Node Draw Order" id="includelayer.afterland6"/>
	<layer xsi:type="includeFileLayer" enabled="true" name="After Land 7" layerId="AfterLand7" KindMain="Special Constructions" KindSub="Layer in Node Draw Order" id="includelayer.afterland7"/>
	<layer xsi:type="includeFileLayer" enabled="true" name="After Land 8" layerId="AfterLand8" KindMain="Special Constructions" KindSub="Layer in Node Draw Order" id="includelayer.afterland8"/>
	<layer xsi:type="includeFileLayer" enabled="true" name="After Land 9" layerId="AfterLand9" KindMain="Special Constructions" KindSub="Layer in Node Draw Order" id="includelayer.afterland9"/>
	<layer xsi:type="includeFileLayer" enabled="true" name="After Land 10" layerId="AfterLand10" KindMain="Special Constructions" KindSub="Layer in Node Draw Order" id="includelayer.afterland10"/>
	<layer xsi:type="epsLayer" enabled="true" name="hill shading" KindMain="EPS-layers" KindSub="" id="epslayer.hillshading" xmlns:xsi="http://www.w3.org/2001/XMLSchema-instance"/>
	<layer xsi:type="includeFileLayer" enabled="true" name="Vectorlayer Poly" layerId="VectorlayerPoly" KindMain="Special Constructions" KindSub="Layer in Node Draw Order" id="includelayer.vectorlayerpoly"/>
	<layer xsi:type="includeFileLayer" enabled="true" name="Vectorlayer Line" layerId="VectorlayerLine" KindMain="Special Constructions" KindSub="Layer in Node Draw Order" id="includelayer.vectorlayerline"/>
	<layer xsi:type="includeFileLayer" enabled="true" name="Vectorlayer Poi" layerId="VectorlayerPoi" KindMain="Special Constructions" KindSub="Layer in Node Draw Order" id="includelayer.vectorlayerpoi"/>
	<layer xsi:type="includeFileLayer" enabled="true" name="After Roads" layerId="AfterRoads" KindMain="Special Constructions" KindSub="Layer in Node Draw Order" id="includelayer.afterroads"/>
	<layer xsi:type="gridLayer" enabled="true" name="Grid Layer" KindMain="Special Constructions" KindSub="Layer in Node Draw Order" id="layer.grid"/>
	<layer xsi:type="epsLayer" enabled="true" name="island name" KindMain="EPS-layers" KindSub="" id="epslayer.generic.26"/>
	<userstyle xsi:type="polygonaluserstyle" enabled="true" name="Island Name" overwriteRoadclass="motorway" namePattern="(.*)" KindMain="Landuse" KindSub="Islands" id="landuse.islands.label">
		<criteria>
			<equation oper="eq" fieldname="Categ" value="PolyAttribute"/>
		</criteria>
		<textDraw xsi:type="flexTextDraw" enabled="true" alignment="left" capitalMode="allCaps" font="helvetica" relHeight="120" spacing="30" slant="0" underline="false" flexEnabled="true">
			<fontDraw>
				<line enabled="false">
					<color r="255" g="255" b="255" overprint="false"/>
					<size size="3" units="1/10th millimeter" isRelative="false"/>
					<style size="0" units="1/10th millimeter" isRelative="false" style="solid"/>
				</line>
				<fillColor enabled="true" r="95" g="95" b="95" overprint="false"/>
			</fontDraw>
			<size size="6" units="points" isRelative="false"/>
			<boxDraw enabled="false" extraHeight="0">
				<shape shapekind="rectangle">
					<line enabled="false">
						<color r="255" g="255" b="255" overprint="false"/>
						<size size="1" units="1/10th millimeter" isRelative="false"/>
						<style size="0" units="1/10th millimeter" isRelative="false" style="solid"/>
					</line>
					<fillColor enabled="true" r="95" g="95" b="95" overprint="false"/>
				</shape>
			</boxDraw>
			<flexSize min="100" max="150"/>
			<flexSpacing min="100" max="200"/>
		</textDraw>
		<namePosition name="fullyInside"/>
		<namePosition name="partlyInside"/>
	</userstyle>
	<layer xsi:type="epsLayer" enabled="true" name="maplayout" KindMain="EPS-layers" KindSub="" id="epslayer.maplayout" xmlns:xsi="http://www.w3.org/2001/XMLSchema-instance"/>
</mapStyle>